Risc_processor/rtl/Parameter.v
`ifndef PARAMETER_H_
`define PARAMETER_H_



`define col 16    // Width of instruction and data memory words (16 bits)
`define row_i 15  // Number of instructions in instruction memory (addresses 0 to 14, total 15 words)
                  // This number can be changed. Adding more instructions to verify your design is a good idea.
`define row_d 8   // The number of data words in data memory (addresses 0 to 7, total 8 words)
                  // We only use 8 data. Do not change this number. You can change the value of each data inside test.data file. Total number is fixed at 8.


`define filename "./test/memory_trace.txt" 


`define simulation_time #160 

`endif

Risc_processor/rtl/Control_Unit.v
`timescale 1ns / 1ps
// Verilog code for Control Unit
module Control_Unit(
      input [3:0] opcode,        // Opcode from the instruction
      output reg [1:0] alu_op,   // Control signal for ALU operation (to ALU_Control)
      output reg jump,           // Control signal for Jump instruction
      output reg beq,            // Control signal for Branch on Equal instruction
      output reg bne,            // Control signal for Branch on Not Equal instruction
      output reg mem_read,       // Control signal for Data Memory Read
      output reg mem_write,      // Control signal for Data Memory Write
      output reg alu_src,        // Control signal to select ALU second operand (register or immediate)
      output reg reg_dst,        // Control signal to select destination register (rd or rt)
      output reg mem_to_reg,     // Control signal to select data for write-back (ALU result or memory data)
      output reg reg_write       // Control signal for Register File Write Enable
    );

always @(*) begin
 case(opcode) 
 4'b0000:  begin // LW (Load Word) Instruction
   reg_dst    = 1'b0; // Write to rt (instr[8:6])
   alu_src    = 1'b1; // ALU second operand is sign-extended immediate
   mem_to_reg = 1'b1; // Write data from data memory to register
   reg_write  = 1'b1; // Enable register write
   mem_read   = 1'b1; // Enable data memory read
   mem_write  = 1'b0; // Disable data memory write
   beq        = 1'b0; // Not a branch
   bne        = 1'b0; // Not a branch
   alu_op     = 2'b10; // ALU operation for address calculation (ADD)
   jump       = 1'b0; // Not a jump
  end
 4'b0001:  begin // SW (Store Word) Instruction
   reg_dst    = 1'b0; // Not applicable for SW (no reg write)
   alu_src    = 1'b1; // ALU second operand is sign-extended immediate
   mem_to_reg = 1'b0; // Not applicable (no reg write from memory)
   reg_write  = 1'b0; // Disable register write
   mem_read   = 1'b0; // Disable data memory read
   mem_write  = 1'b1; // Enable data memory write
   beq        = 1'b0; // Not a branch
   bne        = 1'b0; // Not a branch
   alu_op     = 2'b10; // ALU operation for address calculation (ADD)
   jump       = 1'b0; // Not a jump
  end
 // Data Processing Instructions (ADD, SUB, INV, LSL, LSR, AND, OR, SLT)
 // These all have similar control signals, differing only in their specific opcode
 // and how the ALU_Control unit translates it to ALU_Cnt.
 // The ALUOp for these is 2'b00, indicating the Opcode directly selects the ALU operation.
 4'b0010:  begin // ADD
   reg_dst    = 1'b1; // Write to ws (instr[5:3])
   alu_src    = 1'b0; // ALU second operand is from register file (rs2)
   mem_to_reg = 1'b0; // Write ALU result to register
   reg_write  = 1'b1; // Enable register write
   mem_read   = 1'b0; // Disable data memory read
   mem_write  = 1'b0; // Disable data memory write
   beq        = 1'b0; // Not a branch
   bne        = 1'b0; // Not a branch
   alu_op     = 2'b00; // ALU operation determined by opcode (for ALU_Control)
   jump       = 1'b0; // Not a jump
  end
 4'b0011:  begin // SUB
   reg_dst    = 1'b1;
   alu_src    = 1'b0;
   mem_to_reg = 1'b0;
   reg_write  = 1'b1;
   mem_read   = 1'b0;
   mem_write  = 1'b0;
   beq        = 1'b0;
   bne        = 1'b0;
   alu_op     = 2'b00;
   jump       = 1'b0;
  end
 4'b0100:  begin // INV
   reg_dst    = 1'b1;
   alu_src    = 1'b0; // Though only one operand, this path is for consistency
   mem_to_reg = 1'b0;
   reg_write  = 1'b1;
   mem_read   = 1'b0;
   mem_write  = 1'b0;
   beq        = 1'b0;
   bne        = 1'b0;
   alu_op     = 2'b00;
   jump       = 1'b0;
  end
 4'b0101:  begin // LSL
   reg_dst    = 1'b1;
   alu_src    = 1'b0;
   mem_to_reg = 1'b0;
   reg_write  = 1'b1;
   mem_read   = 1'b0;
   mem_write  = 1'b0;
   beq        = 1'b0;
   bne        = 1'b0;
   alu_op     = 2'b00;
   jump       = 1'b0;
  end
 4'b0110:  begin // LSR
   reg_dst    = 1'b1;
   alu_src    = 1'b0;
   mem_to_reg = 1'b0;
   reg_write  = 1'b1;
   mem_read   = 1'b0;
   mem_write  = 1'b0;
   beq        = 1'b0;
   bne        = 1'b0;
   alu_op     = 2'b00;
   jump       = 1'b0;
  end
 4'b0111:  begin // AND
   reg_dst    = 1'b1;
   alu_src    = 1'b0;
   mem_to_reg = 1'b0;
   reg_write  = 1'b1;
   mem_read   = 1'b0;
   mem_write  = 1'b0;
   beq        = 1'b0;
   bne        = 1'b0;
   alu_op     = 2'b00;
   jump       = 1'b0;
  end
 4'b1000:  begin // OR
   reg_dst    = 1'b1;
   alu_src    = 1'b0;
   mem_to_reg = 1'b0;
   reg_write  = 1'b1;
   mem_read   = 1'b0;
   mem_write  = 1'b0;
   beq        = 1'b0;
   bne        = 1'b0;
   alu_op     = 2'b00;
   jump       = 1'b0;
  end
 4'b1001:  begin // SLT
   reg_dst    = 1'b1;
   alu_src    = 1'b0;
   mem_to_reg = 1'b0;
   reg_write  = 1'b1;
   mem_read   = 1'b0;
   mem_write  = 1'b0;
   beq        = 1'b0;
   bne        = 1'b0;
   alu_op     = 2'b00;
   jump       = 1'b0;
  end
 4'b1011:  begin // BEQ (Branch on Equal)
   reg_dst    = 1'b0; // No register write
   alu_src    = 1'b0; // ALU compares two registers (rs1, rs2)
   mem_to_reg = 1'b0; // No register write from memory
   reg_write  = 1'b0; // Disable register write
   mem_read   = 1'b0; // Disable data memory read
   mem_write  = 1'b0; // Disable data memory write
   beq        = 1'b1; // Enable Branch on Equal logic
   bne        = 1'b0; // Not a BNE branch
   alu_op     = 2'b01; // ALU operation for comparison (SUB)
   jump       = 1'b0; // Not a jump
  end
 4'b1100:  begin // BNE (Branch on Not Equal)
   reg_dst    = 1'b0; // No register write
   alu_src    = 1'b0; // ALU compares two registers (rs1, rs2)
   mem_to_reg = 1'b0; // No register write from memory
   reg_write  = 1'b0; // Disable register write
   mem_read   = 1'b0; // Disable data memory read
   mem_write  = 1'b0; // Disable data memory write
   beq        = 1'b0; // Not a BEQ branch
   bne        = 1'b1; // Enable Branch on Not Equal logic
   alu_op     = 2'b01; // ALU operation for comparison (SUB)
   jump       = 1'b0; // Not a jump
  end
 4'b1101:  begin // J (Jump) Instruction
   reg_dst    = 1'b0; // No register write
   alu_src    = 1'b0; // Not applicable
   mem_to_reg = 1'b0; // No register write from memory
   reg_write  = 1'b0; // Disable register write
   mem_read   = 1'b0; // Disable data memory read
   mem_write  = 1'b0; // Disable data memory write
   beq        = 1'b0; // Not a branch
   bne        = 1'b0; // Not a branch
   alu_op     = 2'b00; // Not directly used for PC update in JMP
   jump       = 1'b1; // Enable Jump logic
  end   
 default: begin // Default case for unhandled opcodes
    reg_dst    = 1'b1;
    alu_src    = 1'b0;
    mem_to_reg = 1'b0;
    reg_write  = 1'b1;
    mem_read   = 1'b0;
    mem_write  = 1'b0;
    beq        = 1'b0;
    bne        = 1'b0;
    alu_op     = 2'b00;
    jump       = 1'b0; 
  end
 endcase
end
endmodule

Risc_processor/rtl/Data_Memory.v
`include "../rtl/Parameter.v"

module Data_Memory(
  input clk,
  input [15:0] mem_access_addr,
  input [15:0] mem_write_data,
  input mem_write_en,
  input mem_read,
  output [15:0] mem_read_data
);

reg [`col - 1:0] memory [`row_d - 1:0];
integer f;
wire [2:0] ram_addr = mem_access_addr[2:0];

initial begin
  $readmemb("../test/test.data", memory);
  f = $fopen(`filename);
  $monitor(f, "time = %d\n", $time,
           "\tmemory[0] = %b\n", memory[0],
           "\tmemory[1] = %b\n", memory[1],
           "\tmemory[2] = %b\n", memory[2],
           "\tmemory[3] = %b\n", memory[3],
           "\tmemory[4] = %b\n", memory[4],
           "\tmemory[5] = %b\n", memory[5],
           "\tmemory[6] = %b\n", memory[6],
           "\tmemory[7] = %b\n", memory[7]);
  `simulation_time;
  $fclose(f);
end

always @(posedge clk) begin
  if (mem_write_en)
    memory[ram_addr] <= mem_write_data;
end

assign mem_read_data = (mem_read) ? memory[ram_addr] : 16'd0;

endmodule

Risc_processor/rtl/ALU.v
module ALU(
 input  [15:0] a,  //src1
 input  [15:0] b,  //src2
 input  [2:0] alu_control, //function sel
 
 output reg [15:0] result,  //result 
 output zero
    );

always @(*) begin 
 case(alu_control)
 3'b000: result = a + b; // add
 3'b001: result = a - b; // sub
 3'b010: result = ~a;    // 1's complement (INV)
 3'b011: result = a << b; // Logical Shift Left (LSL)
 3'b100: result = a >> b; // Logical Shift Right (LSR)
 3'b101: result = a & b; // Bitwise AND
 3'b110: result = a | b; // Bitwise OR
 3'b111: begin // Set on Less Than (SLT)
    if (a < b) 
        result = 16'd1;
    else 
        result = 16'd0;
    end
 default:result = a + b; // Default to add
 endcase
end

// Zero flag assignment: set to 1 if result is 0, otherwise 0
assign zero = (result == 16'd0) ? 1'b1 : 1'b0;

endmodule

Risc_processor/rtl/ALU_Control.v
`timescale 1ns / 1ps

module alu_control(
  output reg [2:0] ALU_Cnt, // ALU control signal
  input [1:0] ALUOp,        // ALU operation type
  input [3:0] Opcode        // Instruction opcode
);

wire [5:0] ALUControlIn;
assign ALUControlIn = {ALUOp, Opcode};

always @(ALUControlIn) begin
  casex (ALUControlIn)
    6'b00_0010: ALU_Cnt = 3'b000; // ADD
    6'b00_0011: ALU_Cnt = 3'b001; // SUB
    6'b00_0100: ALU_Cnt = 3'b010; // INV
    6'b00_0101: ALU_Cnt = 3'b011; // LSL
    6'b00_0110: ALU_Cnt = 3'b100; // LSR
    6'b00_0111: ALU_Cnt = 3'b101; // AND
    6'b00_1000: ALU_Cnt = 3'b110; // OR
    6'b00_1001: ALU_Cnt = 3'b111; // SLT

    6'b10_xxxx: ALU_Cnt = 3'b000; // LW, SW → ADD
    6'b01_xxxx: ALU_Cnt = 3'b001; // BEQ, BNE → SUB

    default:    ALU_Cnt = 3'b000;
  endcase
end

endmodule

Risc_processor/rtl/GPRs.v
`timescale 1ns / 1ps
// Verilog code for register file
module GPRs(
 input    clk,                 // Clock input
 // write port
 input    reg_write_en,        // Register write enable
 input  [2:0] reg_write_dest,  // Destination register address for write
 input  [15:0] reg_write_data, // Data to be written
 //read port 1
 input  [2:0] reg_read_addr_1,  // Read address for port 1
 output  [15:0] reg_read_data_1, // Data read from port 1
 //read port 2
 input  [2:0] reg_read_addr_2,  // Read address for port 2
 output  [15:0] reg_read_data_2  // Data read from port 2
);

// Declare a register array for 8 16-bit general purpose registers
reg [15:0] reg_array [7:0]; 
integer i; // Loop variable for initialization

// Initialize all registers to 0 at the beginning of simulation
initial begin
  for(i = 0; i < 8; i = i + 1) begin
   reg_array[i] <= 16'd0;
  end
end
 
// Always block for register write operation on positive clock edge
always @ (posedge clk ) begin
   if(reg_write_en) begin // If register write is enabled
    reg_array[reg_write_dest] <= reg_write_data; // Write data to the destination register
   end
end
 
// Assign read data directly from the register array (combinational read)
assign reg_read_data_1 = reg_array[reg_read_addr_1]; // Read data from address 1
assign reg_read_data_2 = reg_array[reg_read_addr_2]; // Read data from address 2

endmodule

Risc_processor/rtl/Instruction_Memory.v
`include "../rtl/Parameter.v"

module Instruction_Memory(
  input [15:0] pc,
  output [15:0] instruction
);

reg [`col - 1:0] memory [`row_i - 1:0];
wire [3:0] rom_addr = pc[4:1];

initial begin
  $readmemb("../test/test.prog", memory, 0, 14);
end

assign instruction = memory[rom_addr];

endmodule

Risc_processor/rtl/Datapath_Unit.v
`timescale 1ns / 1ps

module Datapath_Unit(
  input clk,
  input jump,
  input beq,
  input mem_read,
  input mem_write,
  input alu_src,
  input reg_dst,
  input mem_to_reg,
  input reg_write,
  input bne,
  input [1:0] alu_op,
  output [3:0] opcode
);

reg  [15:0] pc_current;
wire [15:0] pc_next, pc2;

wire [15:0] instr;

wire [2:0] reg_write_dest;
wire [15:0] reg_write_data;
wire [2:0] reg_read_addr_1, reg_read_addr_2;
wire [15:0] reg_read_data_1, reg_read_data_2;

wire [15:0] ext_im, read_data2;

wire [2:0] ALU_Control;
wire [15:0] ALU_out;
wire zero_flag;

wire [15:0] PC_j, PC_beq, PC_bne, PC_2beq, PC_2bne;
wire [12:0] jump_shift;
wire beq_control, bne_control;

wire [15:0] mem_read_data;

initial begin
  pc_current <= 16'd0;
end

always @(posedge clk) begin
  pc_current <= pc_next;
end

assign pc2 = pc_current + 16'd2;

Instruction_Memory im(
  .pc(pc_current),
  .instruction(instr)
);

assign jump_shift = {instr[11:0], 1'b0};

assign reg_write_dest = (reg_dst) ? instr[5:3] : instr[8:6];
assign reg_read_addr_1 = instr[11:9];
assign reg_read_addr_2 = instr[8:6];

GPRs reg_file (
  .clk(clk),
  .reg_write_en(reg_write),
  .reg_write_dest(reg_write_dest),
  .reg_write_data(reg_write_data),
  .reg_read_addr_1(reg_read_addr_1),
  .reg_read_data_1(reg_read_data_1),
  .reg_read_addr_2(reg_read_addr_2),
  .reg_read_data_2(reg_read_data_2)
);

assign ext_im = {{10{instr[5]}}, instr[5:0]};

alu_control ALU_Control_unit(
  .ALUOp(alu_op),
  .Opcode(instr[15:12]),
  .ALU_Cnt(ALU_Control)
);

assign read_data2 = (alu_src) ? ext_im : reg_read_data_2;

ALU alu_unit(
  .a(reg_read_data_1),
  .b(read_data2),
  .alu_control(ALU_Control),
  .result(ALU_out),
  .zero(zero_flag)
);

assign PC_beq = pc2 + {ext_im[14:0], 1'b0};
assign PC_bne = pc2 + {ext_im[14:0], 1'b0};
assign beq_control = beq & zero_flag;
assign bne_control = bne & ~zero_flag;
assign PC_2beq = (beq_control) ? PC_beq : pc2;
assign PC_2bne = (bne_control) ? PC_bne : PC_2beq;
assign PC_j = {pc2[15:13], jump_shift};
assign pc_next = (jump) ? PC_j : PC_2bne;

Data_Memory dm (
  .clk(clk),
  .mem_access_addr(ALU_out),
  .mem_write_data(reg_read_data_2),
  .mem_write_en(mem_write),
  .mem_read(mem_read),
  .mem_read_data(mem_read_data)
);

assign reg_write_data = (mem_to_reg) ? mem_read_data : ALU_out;
assign opcode = instr[15:12];

endmodule

Risc_processor/rtl/Risc_16_bit.v
`timescale 1ns / 1ps
// fpga4student.com // FPGA projects, VHDL projects, Verilog projects
// Verilog code for RISC Processor
// Top-level module for the 16-bit RISC processor
module Risc_16_bit(
 input clk // Main clock input for the processor
);

 // Wires for control signals generated by the Control Unit
 wire jump, bne, beq, mem_read, mem_write, alu_src, reg_dst, mem_to_reg, reg_write;
 // Wire for ALU operation type (input to ALU_Control)
 wire[1:0] alu_op;
 // Wire for opcode extracted from instruction (output from Datapath, input to Control Unit)
 wire [3:0] opcode;

 // Instantiate the Datapath Unit
 // This module contains the main dataflow components like PC, Register File, ALU, Memories
 Datapath_Unit DU
 (
  .clk(clk),           // Connect clock
  .jump(jump),         // Connect jump control signal
  .beq(beq),           // Connect branch-on-equal control signal
  .mem_read(mem_read), // Connect memory read control signal
  .mem_write(mem_write),// Connect memory write control signal
  .alu_src(alu_src),   // Connect ALU source select control signal
  .reg_dst(reg_dst),   // Connect register destination select control signal
  .mem_to_reg(mem_to_reg),// Connect memory-to-register write-back select signal
  .reg_write(reg_write),// Connect register write enable signal
  .bne(bne),           // Connect branch-on-not-equal control signal
  .alu_op(alu_op),     // Connect ALU operation type (input)
  .opcode(opcode)      // Connect opcode (output from datapath, input to control)
 );

 // Instantiate the Control Unit
 // This module generates all control signals based on the instruction opcode
 Control_Unit control
 (
  .opcode(opcode),      // Connect opcode (input from datapath)
  .reg_dst(reg_dst),    // Connect register destination select control signal
  .mem_to_reg(mem_to_reg),// Connect memory-to-register write-back select signal
  .alu_op(alu_op),      // Connect ALU operation type (output)
  .jump(jump),          // Connect jump control signal
  .bne(bne),            // Connect branch-on-not-equal control signal
  .beq(beq),            // Connect branch-on-equal control signal
  .mem_read(mem_read),  // Connect memory read control signal
  .mem_write(mem_write),// Connect memory write control signal
  .alu_src(alu_src),    // Connect ALU source select control signal
  .reg_write(reg_write) // Connect register write enable signal
 );

endmodule

Risc_processor/Sim/test_Risc_16_bit.v
`timescale 1ns / 1ps
`include "../rtl/Parameter.v"

module test_Risc_16_bit;

reg clk;

Risc_16_bit uut (
  .clk(clk)
);

initial begin
  $dumpfile("riscv_wave.vcd");
  $dumpvars(0, test_Risc_16_bit);
  $dumpvars(1, uut);
end

initial begin
  clk <= 1'b0;
  `simulation_time;
  $finish;
end

always begin
  #5 clk = ~clk;
end

endmodule

Risc_processor/scripts/riscv_wave.vcd
$date
	Thu Jul  3 00:28:12 2025
$end
$version
	Icarus Verilog
$end
$timescale
	1ps
$end
$scope module test_Risc_16_bit $end
$var reg 1 ! clk $end
$scope module uut $end
$var wire 1 ! clk $end
$var wire 1 " reg_write $end
$var wire 1 # reg_dst $end
$var wire 4 $ opcode [3:0] $end
$var wire 1 % mem_write $end
$var wire 1 & mem_to_reg $end
$var wire 1 ' mem_read $end
$var wire 1 ( jump $end
$var wire 1 ) bne $end
$var wire 1 * beq $end
$var wire 1 + alu_src $end
$var wire 2 , alu_op [1:0] $end
$scope module DU $end
$var wire 1 - beq_control $end
$var wire 1 . bne_control $end
$var wire 1 ! clk $end
$var wire 1 / zero_flag $end
$var wire 3 0 reg_write_dest [2:0] $end
$var wire 16 1 reg_write_data [15:0] $end
$var wire 1 " reg_write $end
$var wire 16 2 reg_read_data_2 [15:0] $end
$var wire 16 3 reg_read_data_1 [15:0] $end
$var wire 3 4 reg_read_addr_2 [2:0] $end
$var wire 3 5 reg_read_addr_1 [2:0] $end
$var wire 1 # reg_dst $end
$var wire 16 6 read_data2 [15:0] $end
$var wire 16 7 pc_next [15:0] $end
$var wire 16 8 pc2 [15:0] $end
$var wire 4 9 opcode [3:0] $end
$var wire 1 % mem_write $end
$var wire 1 & mem_to_reg $end
$var wire 16 : mem_read_data [15:0] $end
$var wire 1 ' mem_read $end
$var wire 13 ; jump_shift [12:0] $end
$var wire 1 ( jump $end
$var wire 16 < instr [15:0] $end
$var wire 16 = ext_im [15:0] $end
$var wire 1 ) bne $end
$var wire 1 * beq $end
$var wire 1 + alu_src $end
$var wire 2 > alu_op [1:0] $end
$var wire 16 ? PC_j [15:0] $end
$var wire 16 @ PC_bne [15:0] $end
$var wire 16 A PC_beq [15:0] $end
$var wire 16 B PC_2bne [15:0] $end
$var wire 16 C PC_2beq [15:0] $end
$var wire 16 D ALU_out [15:0] $end
$var wire 3 E ALU_Control [2:0] $end
$var reg 16 F pc_current [15:0] $end
$scope module ALU_Control_unit $end
$var wire 4 G Opcode [3:0] $end
$var wire 2 H ALUOp [1:0] $end
$var wire 6 I ALUControlIn [5:0] $end
$var reg 3 J ALU_Cnt [2:0] $end
$upscope $end
$scope module alu_unit $end
$var wire 3 K alu_control [2:0] $end
$var wire 16 L b [15:0] $end
$var wire 1 / zero $end
$var wire 16 M a [15:0] $end
$var reg 16 N result [15:0] $end
$upscope $end
$scope module dm $end
$var wire 1 ! clk $end
$var wire 16 O mem_access_addr [15:0] $end
$var wire 3 P ram_addr [2:0] $end
$var wire 1 % mem_write_en $end
$var wire 16 Q mem_write_data [15:0] $end
$var wire 16 R mem_read_data [15:0] $end
$var wire 1 ' mem_read $end
$var integer 32 S f [31:0] $end
$upscope $end
$scope module im $end
$var wire 16 T instruction [15:0] $end
$var wire 16 U pc [15:0] $end
$var wire 4 V rom_addr [3:0] $end
$upscope $end
$scope module reg_file $end
$var wire 1 ! clk $end
$var wire 3 W reg_read_addr_1 [2:0] $end
$var wire 3 X reg_read_addr_2 [2:0] $end
$var wire 16 Y reg_read_data_1 [15:0] $end
$var wire 16 Z reg_read_data_2 [15:0] $end
$var wire 16 [ reg_write_data [15:0] $end
$var wire 3 \ reg_write_dest [2:0] $end
$var wire 1 " reg_write_en $end
$var integer 32 ] i [31:0] $end
$upscope $end
$upscope $end
$scope module control $end
$var wire 4 ^ opcode [3:0] $end
$var reg 2 _ alu_op [1:0] $end
$var reg 1 + alu_src $end
$var reg 1 * beq $end
$var reg 1 ) bne $end
$var reg 1 ( jump $end
$var reg 1 ' mem_read $end
$var reg 1 & mem_to_reg $end
$var reg 1 % mem_write $end
$var reg 1 # reg_dst $end
$var reg 1 " reg_write $end
$upscope $end
$upscope $end
$upscope $end
$scope module test_Risc_16_bit $end
$scope module uut $end
$upscope $end
$upscope $end
$enddefinitions $end
$comment Show the parameter values. $end
$dumpall
$end
#0
$dumpvars
b10 _
b0 ^
b1000 ]
b0 \
b1 [
b0 Z
b0 Y
b0 X
b10 W
b0 V
b0 U
b10000000000 T
b0 S
b1 R
b0 Q
b0 P
b0 O
b0 N
b0 M
b0 L
b0 K
b0 J
b100000 I
b10 H
b0 G
b0 F
b0 E
b0 D
b10 C
b10 B
b10 A
b10 @
b100000000000 ?
b10 >
b0 =
b10000000000 <
b100000000000 ;
b1 :
b0 9
b10 8
b10 7
b0 6
b10 5
b0 4
b0 3
b0 2
b1 1
b0 0
1/
0.
0-
b10 ,
1+
0*
0)
0(
1'
1&
0%
b0 $
0#
1"
0!
$end
#5000
b10 1
b10 [
b10 :
b10 R
0/
b1 P
b1 D
b1 N
b1 O
b100 7
b1 6
b1 L
b1 0
b1 \
b100 B
b1 =
b1 4
b1 X
b100010000010 ?
b100010000010 ;
b100 C
b10001000001 <
b10001000001 T
b1 V
b0 2
b0 Q
b0 Z
b110 A
b110 @
b100 8
b10 F
b10 U
1!
#10000
0!
#15000
b0 :
b0 R
b11 1
b11 [
b10 0
b10 \
b11 P
b110 7
b0 ,
b0 >
b0 H
b0 _
0'
0&
0+
1#
b10 6
b10 L
b11 D
b11 N
b11 O
b110 B
b10 $
b10 9
b10 ^
b10 I
b10 G
b10000 =
b1 3
b1 M
b1 Y
b0 5
b0 W
b10100000 ?
b10100000 ;
b110 C
b10000001010000 <
b10000001010000 T
b10 V
b100110 A
b100110 @
b110 8
b100 F
b100 U
b10 2
b10 Q
b10 Z
1!
#20000
0!
#25000
b10 P
b10 1
b10 [
b1000 7
b10 ,
b10 >
b10 H
b10 _
1%
0"
1+
0#
b0 6
b0 L
b10 D
b10 N
b10 O
b10 0
b10 \
b1000 B
b1 $
b1 9
b1 ^
b100001 I
b1 G
b0 =
b11 2
b11 Q
b11 Z
b10 4
b10 X
b10 3
b10 M
b10 Y
b1 5
b1 W
b10100000000 ?
b10100000000 ;
b1000 C
b1001010000000 <
b1001010000000 T
b11 V
b1000 A
b1000 @
b1000 8
b110 F
b110 U
1!
#30000
0!
#35000
b1 E
b1 J
b1 K
b111 P
b1111111111111111 1
b1111111111111111 [
b1010 7
b0 ,
b0 >
b0 H
b0 _
0%
1"
0+
1#
b10 6
b10 L
b1111111111111111 D
b1111111111111111 N
b1111111111111111 O
b10 0
b10 \
b1010 B
b11 $
b11 9
b11 ^
b11 I
b11 G
b10000 =
b10 2
b10 Q
b10 Z
b1 4
b1 X
b1 3
b1 M
b1 Y
b0 5
b0 W
b10100000 ?
b10100000 ;
b1010 C
b11000001010000 <
b11000001010000 T
b100 V
b101010 A
b101010 @
b1010 8
b1000 F
b1000 U
1!
#40000
0!
#45000
b110 P
b1111111111111110 1
b1111111111111110 [
b1111111111111110 D
b1111111111111110 N
b1111111111111110 O
b1100 7
b10 E
b10 J
b10 K
b1100 B
b100 $
b100 9
b100 ^
b100 I
b100 G
b1100 C
b100000001010000 <
b100000001010000 T
b101 V
b101100 A
b101100 @
b1100 8
b1010 F
b1010 U
1!
#50000
0!
#55000
b100 P
b100 1
b100 [
b100 D
b100 N
b100 O
b1110 7
b11 E
b11 J
b11 K
b1110 B
b101 $
b101 9
b101 ^
b101 I
b101 G
b1110 C
b101000001010000 <
b101000001010000 T
b110 V
b101110 A
b101110 @
b1110 8
b1100 F
b1100 U
1!
#60000
0!
#65000
1/
b0 P
b0 1
b0 [
b0 D
b0 N
b0 O
b10000 7
b100 E
b100 J
b100 K
b10000 B
b110 $
b110 9
b110 ^
b110 I
b110 G
b10000 C
b110000001010000 <
b110000001010000 T
b111 V
b110000 A
b110000 @
b10000 8
b1110 F
b1110 U
1!
#70000
0!
#75000
b10010 7
b101 E
b101 J
b101 K
b10010 B
b111 $
b111 9
b111 ^
b111 I
b111 G
b10010 C
b111000001010000 <
b111000001010000 T
b1000 V
b110010 A
b110010 @
b10010 8
b10000 F
b10000 U
1!
#80000
0!
#85000
0/
b11 P
b11 1
b11 [
b11 D
b11 N
b11 O
b10100 7
b110 E
b110 J
b110 K
b10100 B
b1000 $
b1000 9
b1000 ^
b1000 I
b1000 G
b10100 C
b1000000001010000 <
b1000000001010000 T
b1001 V
b110100 A
b110100 @
b10100 8
b10010 F
b10010 U
1!
#90000
0!
#95000
b1 P
b1 1
b1 [
b1 D
b1 N
b1 O
b10110 7
b111 E
b111 J
b111 K
b10110 B
b1001 $
b1001 9
b1001 ^
b1001 I
b1001 G
b10110 C
b1001000001010000 <
b1001000001010000 T
b1010 V
b110110 A
b110110 @
b10110 8
b10100 F
b10100 U
1!
#100000
0!
#105000
b10 P
b10 1
b10 [
b10 D
b10 N
b10 O
b11000 7
b0 E
b0 J
b0 K
b1 6
b1 L
b0 0
b0 \
b11000 B
b10 $
b10 9
b10 ^
b10 I
b10 G
b0 =
b1 2
b1 Q
b1 Z
b0 4
b0 X
b0 ?
b0 ;
b11000 C
b10000000000000 <
b10000000000000 T
b1011 V
b11000 A
b11000 @
b11000 8
b10110 F
b10110 U
1!
#110000
0!
#115000
1-
1/
b1 E
b1 J
b1 K
b1 0
b1 \
b11100 7
b1 ,
b1 >
b1 H
b1 _
1*
0"
0#
b11100 B
b1011 $
b1011 9
b1011 ^
b11011 I
b1011 G
b1 =
b1 4
b1 X
b10000010 ?
b10000010 ;
b0 P
b0 1
b0 [
b11100 C
b1011000001000001 <
b1011000001000001 T
b1100 V
b0 D
b0 N
b0 O
b10 6
b10 L
b11100 A
b11100 @
b11010 8
b11000 F
b11000 U
b10 3
b10 M
b10 Y
b10 2
b10 Q
b10 Z
1!
#120000
0!
#125000
0/
b100 P
b100 1
b100 [
b100 D
b100 N
b100 O
b0 E
b0 J
b0 K
0-
b0 7
1(
b0 ,
b0 >
b0 H
b0 _
0*
b0 0
b0 \
b11110 B
b1101 $
b1101 9
b1101 ^
b1101 I
b1101 G
b0 =
b0 4
b0 X
b0 ?
b0 ;
b11110 C
b1101000000000000 <
b1101000000000000 T
b1110 V
b11110 A
b11110 @
b11110 8
b11100 F
b11100 U
1!
#130000
0!
#135000
b10 :
b10 R
b0 6
b0 L
b1 P
b10 1
b10 [
0(
b10 ,
b10 >
b10 H
b10 _
1'
1"
1&
1+
b1 D
b1 N
b1 O
b10 7
b10 B
b0 $
b0 9
b0 ^
b100000 I
b0 G
b1 3
b1 M
b1 Y
b10 5
b10 W
b100000000000 ?
b100000000000 ;
b10 C
b10000000000 <
b10000000000 T
b0 V
b10 A
b10 @
b10 8
b0 F
b0 U
1!
#140000
0!
#145000
b11 1
b11 [
b11 :
b11 R
b10 P
b10 D
b10 N
b10 O
b100 7
b1 6
b1 L
b1 0
b1 \
b100 B
b1 =
b1 4
b1 X
b100010000010 ?
b100010000010 ;
b100 C
b10001000001 <
b10001000001 T
b1 V
b110 A
b110 @
b100 8
b10 F
b10 U
1!
#150000
0!
#155000
b0 :
b0 R
b101 1
b101 [
b10 0
b10 \
b101 P
b110 7
b0 ,
b0 >
b0 H
b0 _
0'
0&
0+
1#
b11 6
b11 L
b101 D
b101 N
b101 O
b110 B
b10 $
b10 9
b10 ^
b10 I
b10 G
b10000 =
b10 3
b10 M
b10 Y
b0 5
b0 W
b10100000 ?
b10100000 ;
b110 C
b10000001010000 <
b10000001010000 T
b10 V
b100110 A
b100110 @
b110 8
b100 F
b100 U
b11 2
b11 Q
b11 Z
1!
